{
  "kind": "collectionType",
  "collectionName": "type_dishes",
  "info": {
    "singularName": "type-dish",
    "pluralName": "type-dishes",
    "displayName": "TypeDish"
  },
  "options": {
    "draftAndPublish": false
  },
  "pluginOptions": {
    "i18n": {
      "localized": true
    }
  },
  "attributes": {
    "color": {
      "pluginOptions": {
        "i18n": {
          "localized": true
        },
        "translate": {
          "translate": "translate"
        }
      },
      "type": "string"
    },
    "icon": {
      "allowedTypes": [
        "images",
        "files",
        "videos",
        "audios"
      ],
      "type": "media",
      "multiple": false,
      "pluginOptions": {
        "i18n": {
          "localized": true
        },
        "translate": {
          "translate": "translate"
        }
      }
    }
  }
}
